state_service_enums/__init__.py
state_service_enums/enums.py
vtb_state_service_enums-1.3.1.dist-info/METADATA
vtb_state_service_enums-1.3.1.dist-info/WHEEL
vtb_state_service_enums-1.3.1.dist-info/top_level.txt
vtb_state_service_enums-1.3.1.dist-info/RECORD
