Metadata-Version: 2.1
Name: vtb-state-service-enums
Version: 1.3.1
Summary: enums for VTB state service
Home-page: https://bitbucket.org/Michail_Shutov/state_service_enums
Author: Mikhail Shutov
Author-email: michael-russ@yandex.ru
License: UNKNOWN
Platform: UNKNOWN
